pyscn_mcp-1.9.2.dist-info/METADATA
pyscn_mcp-1.9.2.dist-info/WHEEL
pyscn_mcp-1.9.2.dist-info/entry_points.txt
pyscn_mcp/__init__.py
pyscn_mcp/__main__.py
pyscn_mcp/bin/pyscn-mcp-darwin-arm64
pyscn_mcp-1.9.2.dist-info/RECORD
